riskcal/__init__.py
riskcal/accountants/__init__.py
riskcal/accountants/ctd.py
riskcal/analysis/__init__.py
riskcal/analysis/_plrv.py
riskcal/analysis/conversions.py
riskcal/blackbox.py
riskcal/calibration/__init__.py
riskcal/calibration/blackbox.py
riskcal/calibration/core.py
riskcal/calibration/dpsgd.py
riskcal/conversions.py
riskcal/dpsgd.py
riskcal/plrv.py
riskcal/utils.py
riskcal-1.3.0.dist-info/licenses/LICENSE
riskcal-1.3.0.dist-info/WHEEL
riskcal-1.3.0.dist-info/METADATA
riskcal-1.3.0.dist-info/RECORD
