Metadata-Version: 2.4
Name: riskcal
Version: 1.3.0
Summary: Compute f-DP trade-off curves and calibrate differentially private algorithms to operational privacy risk measures
Keywords: privacy,differential privacy
Author: Bogdan Kulynych, Juan Felipe Gomez
Author-email: Bogdan Kulynych <bogdan@kulyny.ch>, Juan Felipe Gomez <gomezjuan772@gmail.com>
License-Expression: MIT
License-File: LICENSE
Classifier: Development Status :: 3 - Alpha
Classifier: Intended Audience :: Science/Research
Requires-Dist: dp-accounting==0.4.4
Requires-Dist: scipy>=1.11.3
Requires-Dist: sphinx>=7.0.0 ; extra == 'docs'
Requires-Dist: sphinx-rtd-theme>=2.0.0 ; extra == 'docs'
Requires-Dist: sphinx-copybutton>=0.5.0 ; extra == 'docs'
Requires-Dist: myst-parser>=2.0.0 ; extra == 'docs'
Requires-Dist: nbsphinx>=0.9.0 ; extra == 'docs'
Requires-Dist: ipython>=8.0.0 ; extra == 'docs'
Requires-Dist: ipykernel>=6.0.0 ; extra == 'docs'
Requires-Dist: linkify-it-py>=2.0.3 ; extra == 'docs'
Requires-Python: >=3.9
Project-URL: Repository, https://github.com/Felipe-Gomez/riskcal.git
Provides-Extra: docs
